simple_talking_anime_avatar/__init__.py
simple_talking_anime_avatar/avatar_gen.py
simple_talking_anime_avatar/speech_to_vid.py
simple_talking_anime_avatar/character_images/female1/main_image.png
simple_talking_anime_avatar/character_images/female1/mouth_aei.png
simple_talking_anime_avatar/character_images/female1/mouth_bmp.png
simple_talking_anime_avatar/character_images/female1/mouth_cdgknstxyz.png
simple_talking_anime_avatar/character_images/female1/mouth_chjsh.png
simple_talking_anime_avatar/character_images/female1/mouth_ee.png
simple_talking_anime_avatar/character_images/female1/mouth_fv.png
simple_talking_anime_avatar/character_images/female1/mouth_l.png
simple_talking_anime_avatar/character_images/female1/mouth_o.png
simple_talking_anime_avatar/character_images/female1/mouth_r.png
simple_talking_anime_avatar/character_images/female1/mouth_th.png
simple_talking_anime_avatar/character_images/female1/mouth_u.png
simple_talking_anime_avatar/character_images/female1/mouth_wq.png
simple_talking_anime_avatar-0.0.6.dist-info/METADATA
simple_talking_anime_avatar-0.0.6.dist-info/WHEEL
simple_talking_anime_avatar-0.0.6.dist-info/licenses/LICENSE
simple_talking_anime_avatar-0.0.6.dist-info/RECORD
