Metadata-Version: 2.4
Name: simple-talking_anime-avatar
Version: 0.0.6
Summary: A simple python package to generate image or video of a talking avatar based on text or audio.
Project-URL: Homepage, https://github.com/snow884/simple_talking_anime_avatar
Project-URL: Bug Tracker, https://github.com/snow884/simple_talking_anime_avatar/issues
Author-email: Adam Ivansky <adam.ivansky@gmail.com>
License-File: LICENSE
Classifier: License :: OSI Approved :: MIT License
Classifier: Operating System :: OS Independent
Classifier: Programming Language :: Python :: 3
Requires-Python: >=3.10
Requires-Dist: librosa>=0.10.0
Requires-Dist: moviepy>=2.0.0
Requires-Dist: numpy<2.0.0,>=1.20.0
Requires-Dist: opencv-python>=4.0.0.21
Requires-Dist: whisper-timestamped>=1.15.8
Requires-Dist: whisper>=1.1.10
